fairness/__init__.py
fairness/adapters.py
fairness/data.py
fairness/groups.py
fairness/metrics.py
fairness/preprocess.py
fairness/single_metrics.py
fairness/visualisation.py
fairness/utils/__init__.py
fairness/utils/pipeline.py
intersectional_fairness_toolkit-1.0.0.dist-info/licenses/LICENSE
intersectional_fairness_toolkit-1.0.0.dist-info/METADATA
intersectional_fairness_toolkit-1.0.0.dist-info/WHEEL
intersectional_fairness_toolkit-1.0.0.dist-info/top_level.txt
intersectional_fairness_toolkit-1.0.0.dist-info/RECORD
