Metadata-Version: 2.4
Name: intersectional-fairness-toolkit
Version: 1.0.0
Summary: Utilities for intersectional fairness analysis of tabular health datasets.
Author: Raiet Bekirov, Nick Berry, Becky Griffiths, Kayla Yasmine
License: Apache 2.0
Project-URL: Homepage, https://raiet-bekirov.github.io/HPDM139_assignment/
Project-URL: Repository, https://github.com/raiet-bekirov/HPDM139_assignment
Requires-Python: >=3.10
License-File: LICENSE
Requires-Dist: pandas>=2.0
Requires-Dist: numpy>=1.24
Requires-Dist: scikit-learn>=1.3
Requires-Dist: matplotlib>=3.7
Provides-Extra: dev
Requires-Dist: pytest>=7.0; extra == "dev"
Dynamic: license-file
